draping/__init__.py
draping/draping.py
draping-0.5.4.dist-info/licenses/LICENSE
examples/draping_async.py
examples/draping_sync.py
tests/draping_subjects.py
tests/test_draping_async.py
tests/test_draping_sync.py
tests/test_helpers.py
draping-0.5.4.dist-info/METADATA
draping-0.5.4.dist-info/WHEEL
draping-0.5.4.dist-info/top_level.txt
draping-0.5.4.dist-info/RECORD
